[
  {
    "account": "agscottpruitt",
    "id": 80911302,
    "linked": "scottpruittok",
    "name": "Scott Pruitt",
    "title": "Administrator of the Environmental Protection Agency"
  },
  {
    "account": "donaldjtrumpjr",
    "id": 39344374,
    "linked": "",
    "name": "Donald Trump Jr.",
    "title": "son"
  },
  {
    "account": "erictrump",
    "id": 39349894,
    "linked": "",
    "name": "Eric Trump",
    "title": "son"
  },
  {
    "account": "genflynn",
    "id": 240454812,
    "linked": "",
    "name": "Michael Flynn",
    "title": "National Security Advisor"
  },
  {
    "account": "ivankatrump",
    "id": 52544275,
    "linked": "",
    "name": "Ivanka Trump",
    "title": "daughter"
  },
  {
    "account": "realbencarson",
    "id": 1180379185,
    "linked": "",
    "name": "Ben Carson",
    "title": "Secretary of Housing and Urban Development"
  },
  {
    "account": "realdonaldtrump",
    "id": 25073877,
    "linked": "",
    "name": "Donald Trump",
    "title": "President"
  },
  {
    "account": "reptomprice",
    "id": 6577802,
    "linked": "",
    "name": "Tom Price",
    "title": "Secretary of Health and Human Services"
  },
  {
    "account": "seanhannity",
    "id": 41634520,
    "linked": "",
    "name": "Sean Hannity",
    "title": "conservative commentator"
  },
  {
    "account": "sheriffclarke",
    "id": 118845216,
    "linked": "",
    "name": "David A. Clarke",
    "title": "Sheriff of Milwaukee County"
  },
  {
    "account": "stephenbannon",
    "id": 114547606,
    "linked": "",
    "name": "Stephen Bannon",
    "title": "Chief Strategist"
  },
  {
    "account": "andypuzder",
    "id": 17494466,
    "linked": "",
    "name": "Andy Puzder",
    "title": "Secretary of Labor"
  },
  {
    "account": "clewandowski_",
    "id": 4121225056,
    "linked": "",
    "name": "Corey Lewandowski",
    "title": "advisor"
  },
  {
    "account": "coburnforsenate",
    "id": 88754581,
    "linked": "",
    "name": "Tom Coburn",
    "title": "former senator"
  },
  {
    "account": "governorperry",
    "id": 18906561,
    "linked": "",
    "name": "Rick Perry",
    "title": "Secretary of Energy"
  },
  {
    "account": "jasonmillerindc",
    "id": 1084375028,
    "linked": "",
    "name": "Jason Miller",
    "title": "transition team"
  },
  {
    "account": "kellyannepolls",
    "id": 471672239,
    "linked": "",
    "name": "Kellyanne Conway",
    "title": "Counselor to the President"
  },
  {
    "account": "larry_kudlow",
    "id": 44401911,
    "linked": "",
    "name": "Larry Kudlow",
    "title": "economic analyst"
  },
  {
    "account": "nikkihaley",
    "id": 37666984,
    "linked": "govhaleysc",
    "name": "Nikki Haley",
    "title": "U.S. Ambassador to United Nations"
  },
  {
    "account": "petehoekstra",
    "id": 15661604,
    "linked": "",
    "name": "Pete Hoekstra",
    "title": "former congressman"
  },
  {
    "account": "reince",
    "id": 20733972,
    "linked": "",
    "name": "Reince Priebus",
    "title": "Chief of Staff"
  },
  {
    "account": "repmickmulvaney",
    "id": 240385577,
    "linked": "",
    "name": "Mick Mulvaney",
    "title": "Director of Office of Management and Budget"
  },
  {
    "account": "repmikepompeo",
    "id": 244268646,
    "linked": "",
    "name": "Mike Pompeo",
    "title": "CIA Director"
  },
  {
    "account": "repmikerogers",
    "id": 156703580,
    "linked": "",
    "name": "Mike Rogers",
    "title": "congressman"
  },
  {
    "account": "ryanzinke",
    "id": 1906282568,
    "linked": "",
    "name": "Ryan Zinke",
    "title": "Secretary of Interior"
  },
  {
    "account": "seanspicer",
    "id": 20776147,
    "linked": "",
    "name": "Sean Spicer",
    "title": "Press Secretary"
  },
  {
    "account": "senatorsessions",
    "id": 47975734,
    "linked": "",
    "name": "Jeff Sessions",
    "title": "Attorney General"
  },
  {
    "account": "rogerjstonejr",
    "id": 47253057,
    "linked": "",
    "name": "Roger Stone",
    "title": "advisor"
  },
  {
    "account": "linda_mcmahon",
    "id": 65522706,
    "linked": "",
    "name": "Linda McMahon",
    "title": "Administrator of the Small Business Administration"
  },
  {
    "account": "pambondi",
    "id": 93755660,
    "linked": "",
    "name": "Pam Bondi",
    "title": "Florida Attorney General"
  },
  {
    "account": "sarahpalinusa",
    "id": 65493023,
    "linked": "",
    "name": "Sarah Palin",
    "title": "former Vice Presidential candidate"
  },
  {
    "account": "danscavino",
    "id": 620571475,
    "linked": "",
    "name": "Dan Scavino",
    "title": "Director of Social Media"
  },
  {
    "account": "sendancoats",
    "id": 212262370,
    "linked": "",
    "name": "Dan Coats",
    "title": "Director of National Intelligence"
  },
  {
    "account": "monicacrowley",
    "id": 166990746,
    "linked": "",
    "name": "Monica Crowley",
    "title": "conservative commentator"
  },
  {
    "account": "tedcruz",
    "id": 23022687,
    "linked": "",
    "name": "Ted Cruz",
    "title": "senator"
  }
]
