[{"retweet_count": 0, "source": "Twitter for iPhone", "created_at": "Tue Dec 25 23:34:05 +0000 2012", "is_retweet": false, "favorite_count": 0, "text": "@TrumpGolfNY to you as well Dan! And, a very healthy and happy new year!", "id_str": "283717279844274176", "in_reply_to_screen_name": "DanScavino"}, {"retweet_count": 0, "source": "Twitter for iPhone", "created_at": "Tue Dec 18 12:27:12 +0000 2012", "is_retweet": false, "favorite_count": 0, "text": "Turning out to be an unbelievable week...first a visit to the office by Shaq and now off today to Vegas for Miss Universe Pageant!", "id_str": "281012739172859904", "in_reply_to_screen_name": null}, {"retweet_count": 0, "source": "Twitter for iPhone", "created_at": "Mon Dec 17 02:02:52 +0000 2012", "is_retweet": false, "favorite_count": 0, "text": "Incredible strength just demonstrated by POTUS in giving the memorial speech at Newtown. Tragic and unnecessary!", "id_str": "280493230708109312", "in_reply_to_screen_name": null}, {"retweet_count": 0, "source": "Twitter for iPhone", "created_at": "Sat Dec 15 21:38:04 +0000 2012", "is_retweet": false, "favorite_count": 0, "text": "@Weatherford5 you can by coming and visiting me at Trump Tower Grill for a Mar a Lago burger...hope to see you soon!", "id_str": "280064204017389569", "in_reply_to_screen_name": "Weatherford5"}, {"retweet_count": 0, "source": "Twitter for iPhone", "created_at": "Sat Dec 15 20:43:49 +0000 2012", "is_retweet": false, "favorite_count": 0, "text": "@MonaB2010 you are pathetic! You should change your screen name as you disgrace the President and all Americans by playing off of his name.", "id_str": "280050551893422080", "in_reply_to_screen_name": "MonaB2010"}, {"retweet_count": 0, "source": "Twitter for iPhone", "created_at": "Sat Dec 15 20:29:43 +0000 2012", "is_retweet": false, "favorite_count": 0, "text": "@MonaB2010 you should be ashamed of yourself! The country mourns and you spew hatred. Disgraceful!", "id_str": "280047003101188096", "in_reply_to_screen_name": "MonaB2010"}, {"retweet_count": 1, "source": "Twitter for iPhone", "created_at": "Fri Dec 14 20:38:43 +0000 2012", "is_retweet": false, "favorite_count": 1, "text": "Our hearts and prayers go out to all those affected by this irrational act committed by a troubled individual in Newtown,CT.", "id_str": "279686880612728832", "in_reply_to_screen_name": null}, {"retweet_count": 7, "source": "Twitter for iPhone", "created_at": "Fri Dec 14 01:15:48 +0000 2012", "is_retweet": false, "favorite_count": 2, "text": "I am so proud to be a part of this amazing group for an amazing cause! @EricTrump, @EricTrumpFdn &amp; @StJude", "id_str": "279394225639022592", "in_reply_to_screen_name": null}, {"retweet_count": 4, "source": "Twitter for iPhone", "created_at": "Fri Dec 14 01:14:00 +0000 2012", "is_retweet": false, "favorite_count": 2, "text": "Great article... $20M Eric Trump Foundation Surgical &amp; ICU Center to open in 2015.\nhttp://t.co/ZYCz2PNT \n@EricTrump @EricTrumpFdn @StJude", "id_str": "279393770531848192", "in_reply_to_screen_name": "EricTrump"}, {"retweet_count": 17, "source": "Twitter for iPhone", "created_at": "Mon Dec 10 15:51:49 +0000 2012", "is_retweet": false, "favorite_count": 5, "text": "@lord_sugar I work for the man and have his complete financials. I can assure you he has very little debt...even you would be impressed!", "id_str": "278165128774557697", "in_reply_to_screen_name": "Lord_Sugar"}, {"retweet_count": 3, "source": "Twitter for iPhone", "created_at": "Wed Nov 28 00:52:51 +0000 2012", "is_retweet": false, "favorite_count": 2, "text": "Thank you to everyone who RT @vanessariddle to make this wonderful young girl's wish come true. Please follow her! Thanks @ericbolling", "id_str": "273590244069236736", "in_reply_to_screen_name": null}, {"retweet_count": 85, "source": "Twitter for iPhone", "created_at": "Tue Nov 27 18:38:16 +0000 2012", "is_retweet": false, "favorite_count": 10, "text": "Join @ericbolling to get @vanessariddle to 100k followers. Beautiful girl with stage 4 cancer.\n http://t.co/9TMKb8W2", "id_str": "273495973748170752", "in_reply_to_screen_name": null}, {"retweet_count": 1, "source": "Twitter for iPhone", "created_at": "Sat Nov 24 00:23:22 +0000 2012", "is_retweet": false, "favorite_count": 2, "text": "@frankambessi jealousy breeds ugliness...and you are one ugly individual. Shame on you!", "id_str": "272133272996311040", "in_reply_to_screen_name": "frankambessi"}, {"retweet_count": 28, "source": "Twitter for iPhone", "created_at": "Wed Nov 21 21:26:23 +0000 2012", "is_retweet": false, "favorite_count": 8, "text": "Glad to see @realDonaldTrump\u2019s return to the @Late_Show and the enormous success it had in ratings. Congrats to both Donald and Dave.", "id_str": "271363954125721600", "in_reply_to_screen_name": null}, {"retweet_count": 16, "source": "Twitter for iPhone", "created_at": "Tue Nov 20 20:26:33 +0000 2012", "is_retweet": false, "favorite_count": 5, "text": "Via @econcrash: \"Donald Trump makes a $1 million splash for Toronto community centre\" http://t.co/ZVIVLo75", "id_str": "270986509543419905", "in_reply_to_screen_name": null}, {"retweet_count": 11, "source": "Twitter for iPhone", "created_at": "Tue Nov 20 18:48:16 +0000 2012", "is_retweet": false, "favorite_count": 1, "text": "@realDonaldTrump The big Herald Square protest was a complete failure with less than 20 people participating. All hype and no legitimacy!", "id_str": "270961776982638592", "in_reply_to_screen_name": "realDonaldTrump"}, {"retweet_count": 0, "source": "Twitter for iPhone", "created_at": "Sat Nov 10 19:58:18 +0000 2012", "is_retweet": false, "favorite_count": 0, "text": "@MorganWoolard let's go. Just pick a date.", "id_str": "267355520669741056", "in_reply_to_screen_name": "MrsMorganMorris"}, {"retweet_count": 1, "source": "Twitter for iPhone", "created_at": "Sat Nov 10 19:34:09 +0000 2012", "is_retweet": false, "favorite_count": 0, "text": "@MorganWoolard then let's go...get here soon for some good food and hang out!", "id_str": "267349444591230976", "in_reply_to_screen_name": "MrsMorganMorris"}, {"retweet_count": 0, "source": "Twitter for iPhone", "created_at": "Sat Nov 10 19:13:56 +0000 2012", "is_retweet": false, "favorite_count": 0, "text": "@MorganWoolard love the pics!!!", "id_str": "267344355587657728", "in_reply_to_screen_name": "MrsMorganMorris"}, {"retweet_count": 0, "source": "Twitter for iPhone", "created_at": "Sat Nov 10 14:20:07 +0000 2012", "is_retweet": false, "favorite_count": 0, "text": "@bretmichaels  hey brother. Hope you are doing well and wanted to just say hi.", "id_str": "267270415158763520", "in_reply_to_screen_name": "bretmichaels"}, {"retweet_count": 0, "source": "Twitter for iPhone", "created_at": "Sat Nov 10 14:09:07 +0000 2012", "is_retweet": false, "favorite_count": 1, "text": "@BethyLM \nI tried to contact him on his cell and campaign office number. No return call. He knows what he did was wrong!", "id_str": "267267647912169472", "in_reply_to_screen_name": "Denali_Beth"}, {"retweet_count": 0, "source": "Twitter Web Client", "created_at": "Sat Nov 10 13:52:07 +0000 2012", "is_retweet": false, "favorite_count": 0, "text": "My family still suffering on south shore with no power. @Realdonaldtrump should take over LIPA and fix it like he did Wollman Rink!", "id_str": "267263371173318656", "in_reply_to_screen_name": null}, {"retweet_count": 0, "source": "Twitter Web Client", "created_at": "Tue Oct 09 01:55:07 +0000 2012", "is_retweet": false, "favorite_count": 0, "text": "@bravosphere @avivadrescher\nBecause it is all about Ramona. If it's not, then move on to the next topic...so long as its about Ramona.", "id_str": "255486520625070080", "in_reply_to_screen_name": "bravosphere"}, {"retweet_count": 0, "source": "Twitter Web Client", "created_at": "Tue Oct 09 01:50:55 +0000 2012", "is_retweet": false, "favorite_count": 0, "text": "@bravosphere @AvivaDrescher \nAnd of course, more eye rolling and weird behavior by the drunken duo!", "id_str": "255485460460212225", "in_reply_to_screen_name": "bravosphere"}, {"retweet_count": 0, "source": "Twitter Web Client", "created_at": "Tue Oct 09 01:36:25 +0000 2012", "is_retweet": false, "favorite_count": 0, "text": "@sonjatmorgan @ramonasinger @AvivaDrescher\nSonja and Ramona...2 bobble heads of nastiness, ugliness and heartless", "id_str": "255481811478642688", "in_reply_to_screen_name": "SonjatMorgan"}, {"retweet_count": 0, "source": "Twitter Web Client", "created_at": "Sat Sep 29 04:02:40 +0000 2012", "is_retweet": false, "favorite_count": 0, "text": "@MsFran53 @samanthanoto @KerPosibilities @AvivaDrescher\nAgreed...good night and sweet dreams", "id_str": "251894738402295810", "in_reply_to_screen_name": "MsFran53"}, {"retweet_count": 0, "source": "Twitter Web Client", "created_at": "Sat Sep 29 03:55:59 +0000 2012", "is_retweet": false, "favorite_count": 0, "text": "@MsFran53 @KerPosibilities @samanthanoto @AvivaDrescher \nThen lay off the crack. It will make you dumber that you already are", "id_str": "251893059321737218", "in_reply_to_screen_name": "MsFran53"}, {"retweet_count": 0, "source": "Twitter Web Client", "created_at": "Sat Sep 29 03:54:37 +0000 2012", "is_retweet": false, "favorite_count": 0, "text": "@KerPosibilities @samanthanoto @MsFran53 \nAnd only 4 year olds use cartoons for theirs.", "id_str": "251892711878189056", "in_reply_to_screen_name": "KerryBBN"}, {"retweet_count": 1, "source": "Twitter Web Client", "created_at": "Sat Sep 29 03:53:36 +0000 2012", "is_retweet": false, "favorite_count": 0, "text": "@MsFran53 @KerPosibilities @samanthanoto @AvivaDrescher\nCare for some more Ramona Pinot you drunken fool!", "id_str": "251892455732019200", "in_reply_to_screen_name": "MsFran53"}, {"retweet_count": 0, "source": "Twitter Web Client", "created_at": "Sat Sep 29 03:51:12 +0000 2012", "is_retweet": false, "favorite_count": 0, "text": "@samanthanoto \nCan't be belly up if it never got started. They must be using the proceeds of her many business ventures to fund this stratup", "id_str": "251891851748061184", "in_reply_to_screen_name": null}, {"retweet_count": 0, "source": "Twitter Web Client", "created_at": "Sat Sep 29 03:48:54 +0000 2012", "is_retweet": false, "favorite_count": 0, "text": "@Kharryan @MsFran53 \nGreat..and now enters the second asshole of the night with some brilliance to share on life", "id_str": "251891276209872896", "in_reply_to_screen_name": "Kharryan"}, {"retweet_count": 0, "source": "Twitter Web Client", "created_at": "Sat Sep 29 03:46:57 +0000 2012", "is_retweet": false, "favorite_count": 0, "text": "@KerPosibilities @AvivaDrescher @MsFran53 Aviva doesn't hate anyone and she was certainly within her right to feel the way she did.", "id_str": "251890782754193410", "in_reply_to_screen_name": "KerryBBN"}, {"retweet_count": 0, "source": "Twitter Web Client", "created_at": "Sat Sep 29 03:44:49 +0000 2012", "is_retweet": false, "favorite_count": 0, "text": "@samanthanoto @MsFran53 \nCan't even find it to buy. Maybe because the entire stock is in her apartment for her personal consumptipn", "id_str": "251890248164966400", "in_reply_to_screen_name": null}, {"retweet_count": 1, "source": "Twitter Web Client", "created_at": "Sat Sep 29 03:39:30 +0000 2012", "is_retweet": false, "favorite_count": 0, "text": "@MsFran53 @AvivaDrescher \nAnd you are a loser!", "id_str": "251888909024370689", "in_reply_to_screen_name": "MsFran53"}, {"retweet_count": 1, "source": "Twitter Web Client", "created_at": "Sat Sep 29 03:38:45 +0000 2012", "is_retweet": false, "favorite_count": 0, "text": "@MsFran53 \nFeel free to take your psych babble down to the local bar and drown your stupidity in a bottle of Ramona pinot", "id_str": "251888722595950592", "in_reply_to_screen_name": "MsFran53"}, {"retweet_count": 0, "source": "Twitter Web Client", "created_at": "Sat Sep 29 03:36:32 +0000 2012", "is_retweet": false, "favorite_count": 0, "text": "@MsFran53 @AvivaDrescher @SonjatMorgan @ramonasinger \nGo play with your cat...you are a sisgrace", "id_str": "251888161389694976", "in_reply_to_screen_name": "MsFran53"}, {"retweet_count": 0, "source": "Twitter Web Client", "created_at": "Sat Sep 29 03:32:15 +0000 2012", "is_retweet": false, "favorite_count": 0, "text": "@samanthanoto @AvivaDrescher \nCouldn't have said it any better", "id_str": "251887086704136194", "in_reply_to_screen_name": null}, {"retweet_count": 0, "source": "Twitter Web Client", "created_at": "Sat Sep 29 03:29:12 +0000 2012", "is_retweet": false, "favorite_count": 0, "text": "@AvivaDrescher @samanthanoto \nYes we should all accept those who are drunk and stupid...some people just can't help themselves!", "id_str": "251886315380043776", "in_reply_to_screen_name": "AvivaDrescher"}, {"retweet_count": 0, "source": "Twitter Web Client", "created_at": "Sat Sep 29 03:26:34 +0000 2012", "is_retweet": false, "favorite_count": 0, "text": "@Zelda98373 \nOk!", "id_str": "251885653112020992", "in_reply_to_screen_name": "Zelda98373"}, {"retweet_count": 0, "source": "Twitter Web Client", "created_at": "Sat Sep 29 03:25:38 +0000 2012", "is_retweet": false, "favorite_count": 0, "text": "@samanthanoto @AvivaDrescher \nSo right! Can you imagine I their daughters behaved this way? Bad examples", "id_str": "251885418721726464", "in_reply_to_screen_name": null}, {"retweet_count": 1, "source": "Twitter Web Client", "created_at": "Sat Sep 29 03:23:53 +0000 2012", "is_retweet": false, "favorite_count": 0, "text": "@MsFran53 @AvivaDrescher @SonjatMorgan @ramonasinger \nThey turned a magnificent estate into a brothel...you are a great judge of class", "id_str": "251884981201272835", "in_reply_to_screen_name": "MsFran53"}, {"retweet_count": 0, "source": "Twitter Web Client", "created_at": "Sat Sep 29 03:19:12 +0000 2012", "is_retweet": false, "favorite_count": 0, "text": "@MsFran53 @AvivaDrescher @SonjatMorgan @ramonasinger\nFinally a logical and intelligent comment", "id_str": "251883800576000000", "in_reply_to_screen_name": "MsFran53"}, {"retweet_count": 0, "source": "Twitter Web Client", "created_at": "Sat Sep 29 03:17:55 +0000 2012", "is_retweet": false, "favorite_count": 0, "text": "@katiejacobs01 @AvivaDrescher @SonjatMorgan @ramonasinger\nThey turned classy St. Bart's into Hedonism. Disgraceful behavior!", "id_str": "251883476293402624", "in_reply_to_screen_name": "katiejacobs01"}, {"retweet_count": 0, "source": "Twitter Web Client", "created_at": "Sat Sep 29 03:15:37 +0000 2012", "is_retweet": false, "favorite_count": 0, "text": "@blondieblue49 @AvivaDrescher @SonjatMorgan @ramonasinger \nNot moral police...also not a sheep following bad behavior.", "id_str": "251882900411260928", "in_reply_to_screen_name": "blondieblue49"}, {"retweet_count": 0, "source": "Twitter Web Client", "created_at": "Sat Sep 29 03:04:14 +0000 2012", "is_retweet": false, "favorite_count": 0, "text": "@MsFran53 @AvivaDrescher @SonjatMorgan @ramonasinger \nBig difference between being partial and blind...and you are clearly blins", "id_str": "251880034971828224", "in_reply_to_screen_name": "MsFran53"}, {"retweet_count": 0, "source": "Twitter Web Client", "created_at": "Sat Sep 29 02:43:03 +0000 2012", "is_retweet": false, "favorite_count": 0, "text": "@MsFran53 @AvivaDrescher @SonjatMorgan @ramonasinger \nYour response is low class and unfounded", "id_str": "251874703591997440", "in_reply_to_screen_name": "MsFran53"}, {"retweet_count": 0, "source": "Twitter Web Client", "created_at": "Sat Sep 29 02:41:48 +0000 2012", "is_retweet": false, "favorite_count": 0, "text": "@blondieblue49 @AvivaDrescher @SonjatMorgan @ramonasinger \nTrying to deal with these two terrors for months must challenging to anyone", "id_str": "251874387106623489", "in_reply_to_screen_name": "blondieblue49"}, {"retweet_count": 0, "source": "Twitter Web Client", "created_at": "Sat Sep 29 02:38:38 +0000 2012", "is_retweet": false, "favorite_count": 1, "text": "@bravoandy we all saw how Sonja and Ramona behaved. Aviva told it like it was. Aviva is a good person.  She doesn't deserve these people.", "id_str": "251873590344052736", "in_reply_to_screen_name": "Andy"}, {"retweet_count": 0, "source": "Twitter Web Client", "created_at": "Sat Sep 29 02:33:12 +0000 2012", "is_retweet": false, "favorite_count": 0, "text": "@MsFran53 @AvivaDrescher @SonjatMorgan @ramonasinger \nREALLY! We have very different views of what's \"behaving badly\".", "id_str": "251872225702051840", "in_reply_to_screen_name": "MsFran53"}, {"retweet_count": 10, "source": "Twitter Web Client", "created_at": "Sat Sep 29 02:27:55 +0000 2012", "is_retweet": false, "favorite_count": 2, "text": "@AvivaDrescher you told it like it was. We all saw how @sonjatmorgan  and @ramonasinger behaved. U r a good person.  Love u", "id_str": "251870896036380672", "in_reply_to_screen_name": "AvivaDrescher"}, {"retweet_count": 0, "source": "Twitter Web Client", "created_at": "Sun Sep 23 01:48:21 +0000 2012", "is_retweet": false, "favorite_count": 0, "text": "Great dinner at Casa Lever...though the service could be improved!", "id_str": "249686608427753472", "in_reply_to_screen_name": null}, {"retweet_count": 0, "source": "Twitter Web Client", "created_at": "Fri Sep 07 02:24:32 +0000 2012", "is_retweet": false, "favorite_count": 0, "text": "@TheTitanGrp @lsesselmann @KaylynKyle @karinaleblanc \nAre you not aware that I am @michaelcohen212?", "id_str": "243897510077288448", "in_reply_to_screen_name": "MichaelCohen212"}, {"retweet_count": 0, "source": "Twitter Web Client", "created_at": "Sun Sep 02 23:45:53 +0000 2012", "is_retweet": false, "favorite_count": 0, "text": "Enjoying a fun night at LAVO with the family and kid's' friends", "id_str": "242408031336419328", "in_reply_to_screen_name": null}, {"retweet_count": 0, "source": "Twitter Web Client", "created_at": "Sat Sep 01 13:18:27 +0000 2012", "is_retweet": false, "favorite_count": 0, "text": "@realDonaldTrump Unfortunately we may all learn if the American people do not wake up and see what he is doing to this once great Nation!", "id_str": "241887748460515328", "in_reply_to_screen_name": "realDonaldTrump"}, {"retweet_count": 1, "source": "Twitter Web Client", "created_at": "Mon Aug 27 17:36:11 +0000 2012", "is_retweet": false, "favorite_count": 0, "text": "@MorganWoolard\nThank you...hope to see and hear from you soon", "id_str": "240140668431917056", "in_reply_to_screen_name": "MrsMorganMorris"}, {"retweet_count": 0, "source": "Twitter Web Client", "created_at": "Mon Aug 27 13:57:01 +0000 2012", "is_retweet": false, "favorite_count": 0, "text": "@CarolineManzo \nHi Caroline. When are you coming into the city for lunch? It's been too long!", "id_str": "240085512285720576", "in_reply_to_screen_name": "CarolineManzo"}, {"retweet_count": 1, "source": "Twitter Web Client", "created_at": "Mon Aug 27 13:53:24 +0000 2012", "is_retweet": false, "favorite_count": 0, "text": "@jonkbrent \nA total sellout at last nights Republican Party of Sarasota Statesman of the Year Award honoring Donald Trump. Great time!", "id_str": "240084601651990530", "in_reply_to_screen_name": "jonkbrent"}, {"retweet_count": 0, "source": "Twitter Web Client", "created_at": "Mon Aug 27 13:23:53 +0000 2012", "is_retweet": false, "favorite_count": 0, "text": "@360candice\nThanks for the retweet...amazing event last night.", "id_str": "240077175737417728", "in_reply_to_screen_name": "360candice"}, {"retweet_count": 4, "source": "Twitter Web Client", "created_at": "Mon Aug 27 12:44:13 +0000 2012", "is_retweet": false, "favorite_count": 1, "text": "A truly amazing event last night at the Sarasota Republican Party Statesman of the Year Award honoring Donald Trump. A total sellout!", "id_str": "240067190970265600", "in_reply_to_screen_name": null}, {"retweet_count": 0, "source": "Twitter Web Client", "created_at": "Sat Aug 25 13:47:29 +0000 2012", "is_retweet": false, "favorite_count": 0, "text": "Trying so hard to enjoy my birthday today...just not a big fan of getting a year older. I guess better than the alternative...", "id_str": "239358339455279104", "in_reply_to_screen_name": null}, {"retweet_count": 1, "source": "Twitter Web Client", "created_at": "Fri Aug 24 11:24:38 +0000 2012", "is_retweet": false, "favorite_count": 0, "text": "2 days until the RNC and the special surprise by Donald Trump. Make sure to watch for it...it's amazing!", "id_str": "238960001253773312", "in_reply_to_screen_name": null}, {"retweet_count": 0, "source": "Twitter Web Client", "created_at": "Mon Aug 20 02:40:27 +0000 2012", "is_retweet": false, "favorite_count": 0, "text": "@Mytweetradio @realDonaldTrump \nCheck out the great response by Mr. Trump and me to Robert Gibbs comment this morning\n\nhttp://t.co/NEf68LzS", "id_str": "237378535659020290", "in_reply_to_screen_name": "MyTweetRadio"}, {"retweet_count": 1, "source": "Twitter Web Client", "created_at": "Mon Aug 20 02:29:49 +0000 2012", "is_retweet": false, "favorite_count": 1, "text": "Great article on today's mistake by Robert Gibbs...and a response by Mr. Trump and me!\n\nhttp://t.co/NEf68LzS", "id_str": "237375856958382080", "in_reply_to_screen_name": null}, {"retweet_count": 0, "source": "Twitter Web Client", "created_at": "Sun Aug 12 23:02:24 +0000 2012", "is_retweet": false, "favorite_count": 0, "text": "Watch me tomorrow morning on channel 5 at 7:15am on Fox 5 NY with Rosanna Scotto!", "id_str": "234786945849495553", "in_reply_to_screen_name": null}, {"retweet_count": 2, "source": "Twitter Web Client", "created_at": "Thu Aug 09 21:29:08 +0000 2012", "is_retweet": false, "favorite_count": 2, "text": "great quote by me:\nhttp://t.co/G4fLeJp3", "id_str": "233676309992198144", "in_reply_to_screen_name": null}, {"retweet_count": 7, "source": "Twitter Web Client", "created_at": "Tue Aug 07 17:16:14 +0000 2012", "is_retweet": false, "favorite_count": 0, "text": "@RamonaSinger @AvivaDrescher\nRamona should be ashamed of herself for making such deplorable statements about Aviva's mother.", "id_str": "232887890441551873", "in_reply_to_screen_name": "ramonasinger"}, {"retweet_count": 0, "source": "Twitter Web Client", "created_at": "Tue Aug 07 12:29:20 +0000 2012", "is_retweet": false, "favorite_count": 0, "text": "@AshleyTSidman \nis there a reason that you are not following me??? grrrrr", "id_str": "232815688832659456", "in_reply_to_screen_name": "AshleyTSidman"}, {"retweet_count": 1, "source": "Twitter Web Client", "created_at": "Tue Aug 07 10:53:37 +0000 2012", "is_retweet": false, "favorite_count": 0, "text": "My friend @avivadrescher is one class act. You handled the Harry issue with class and elegance. I am proud of you!", "id_str": "232791601972379648", "in_reply_to_screen_name": null}, {"retweet_count": 0, "source": "Twitter Web Client", "created_at": "Tue Aug 07 04:40:52 +0000 2012", "is_retweet": false, "favorite_count": 0, "text": "I hope everyone had a chance to hear me today on American Talk Radio. If not...no worries. I will be on again this week.", "id_str": "232697795679752197", "in_reply_to_screen_name": null}, {"retweet_count": 0, "source": "Twitter Web Client", "created_at": "Sun Aug 05 20:19:26 +0000 2012", "is_retweet": false, "favorite_count": 0, "text": "Just spent a hilarious afternoon with Reid. Aviva and papa George at our home in Bridgehampton. They were the hit of the party!.", "id_str": "232209219745636352", "in_reply_to_screen_name": null}, {"retweet_count": 0, "source": "Twitter Web Client", "created_at": "Sun Aug 05 04:11:58 +0000 2012", "is_retweet": false, "favorite_count": 0, "text": "Quick shout out to Eric Trump and the fantastic work being done at ETF benefitting St. Jude. Did I mention I am on the executive board???", "id_str": "231965749252587520", "in_reply_to_screen_name": null}, {"retweet_count": 0, "source": "Twitter Web Client", "created_at": "Sat Aug 04 23:45:02 +0000 2012", "is_retweet": false, "favorite_count": 0, "text": "Off to Beaumarchais in East Hampton. Hopefully they didn't overbook and force hour long wait for our table", "id_str": "231898569257402369", "in_reply_to_screen_name": null}, {"retweet_count": 1, "source": "Twitter Web Client", "created_at": "Sat Aug 04 11:14:17 +0000 2012", "is_retweet": false, "favorite_count": 1, "text": "Please take the time to read and pass along the attached recent article...for the sake of this country.\nhttp://t.co/xscnMy4e", "id_str": "231709638331101187", "in_reply_to_screen_name": null}, {"retweet_count": 1, "source": "Twitter Web Client", "created_at": "Sat Aug 04 11:11:44 +0000 2012", "is_retweet": false, "favorite_count": 0, "text": "@Joedeoudes \nHoping you and your followwrs enjoyed my article http://t.co/xscnMy4e", "id_str": "231708997458210816", "in_reply_to_screen_name": "Joedeoudes"}, {"retweet_count": 0, "source": "Twitter Web Client", "created_at": "Sat Aug 04 03:49:56 +0000 2012", "is_retweet": false, "favorite_count": 0, "text": "To all my twitter friends, hasta la pasta and have a great night. Speak to you in the am", "id_str": "231597814822629377", "in_reply_to_screen_name": null}, {"retweet_count": 0, "source": "Twitter Web Client", "created_at": "Sat Aug 04 03:20:43 +0000 2012", "is_retweet": false, "favorite_count": 0, "text": "Up until 30 minutes ago I was a friend of the friendless...now I have 60!", "id_str": "231590460106350592", "in_reply_to_screen_name": null}, {"retweet_count": 0, "source": "Twitter Web Client", "created_at": "Sat Aug 04 03:12:57 +0000 2012", "is_retweet": false, "favorite_count": 0, "text": "@marcisperalez @AvivaDrescher she is even better in person.", "id_str": "231588507657854977", "in_reply_to_screen_name": "marcisperalez"}, {"retweet_count": 0, "source": "Twitter Web Client", "created_at": "Sat Aug 04 03:08:57 +0000 2012", "is_retweet": false, "favorite_count": 0, "text": "It's really nice to see that so many people love and respect my friend @avivadrescher", "id_str": "231587501616291840", "in_reply_to_screen_name": null}, {"retweet_count": 1, "source": "Twitter Web Client", "created_at": "Sat Aug 04 02:55:56 +0000 2012", "is_retweet": false, "favorite_count": 2, "text": "It's incredible how every housewife wants to be on The Apprentice. My money is on Aviva to be the next winner!", "id_str": "231584223612522496", "in_reply_to_screen_name": null}, {"retweet_count": 1, "source": "Twitter Web Client", "created_at": "Sat Aug 04 02:44:28 +0000 2012", "is_retweet": false, "favorite_count": 1, "text": "Having a great night with Aviva and Reid #rhony @avivadrescher   George showed up with an erection. :)", "id_str": "231581340628307969", "in_reply_to_screen_name": null}, {"retweet_count": 1, "source": "Twitter Web Client", "created_at": "Mon Jul 30 20:05:37 +0000 2012", "is_retweet": false, "favorite_count": 0, "text": "ok followers. I am now on. Time to let your friends know and follow me!", "id_str": "230031413632700416", "in_reply_to_screen_name": null}]